test/__init__.py
test/test_z_scores.py
z_score_calculator/__init__.py
z_score_calculator/calculator.py
z_score_calculator/plotting_utils.py
z_score_calculator/t_test.py
ZScoreCalculator-1.0.0.dist-info/METADATA
ZScoreCalculator-1.0.0.dist-info/WHEEL
ZScoreCalculator-1.0.0.dist-info/top_level.txt
ZScoreCalculator-1.0.0.dist-info/RECORD
